{
    "dataFlowId": "supplier_address_silver",
    "dataFlowGroup": "tpch_silver",
    "dataFlowType": "standard",
    "sourceSystem": "tpch",
    "sourceType": "delta",
    "sourceViewName": "v_supplier_address",
    "sourceDetails": {
        "database": "{bronze_schema}",
        "table": "supplier_address",
        "cdfEnabled": true,
        "selectExp": ["supplier_id as s_suppkey", "address as s_address", "nat_id as s_nationkey", "load_timestamp"]
    },
    "mode": "stream",
    "targetFormat": "delta",
    "targetDetails": {
        "table": "supplier_address",
        "tableProperties": {
            "delta.enableChangeDataFeed": "true"
        },
        "schemaPath": "supplier_address_schema.json"
    },
    "cdcSettings": {
        "keys": [
            "s_suppkey"
        ],
        "scd_type": "2",
        "sequence_by": "load_timestamp",
        "except_column_list": ["load_timestamp"],
        "ignore_null_updates": false
    }
}