{
    "type": "struct",
    "fields": [
        {
            "name": "customer_id",
            "type": "long",
            "nullable": false,
            "metadata": {}
        },
        {
            "name": "name",
            "type": "string",
            "nullable": false,
            "metadata": {}
        },
        {
            "name": "acctbal",
            "type": "decimal(18, 2)",
            "nullable": false,
            "metadata": {}
        },
        {
            "name": "mktseg",
            "type": "string",
            "nullable": true,
            "metadata": {}
        },
        {
            "name": "load_timestamp",
            "type": "timestamp",
            "nullable": false,
            "metadata": {}
        }
    ]
}